flagopt/__init__.py
flagopt/abstract.py
flagopt/general.py
flagopt/helpers.py
flagopt-0.1.4.dist-info/LICENCE
flagopt-0.1.4.dist-info/METADATA
flagopt-0.1.4.dist-info/WHEEL
flagopt-0.1.4.dist-info/top_level.txt
flagopt-0.1.4.dist-info/RECORD
