Metadata-Version: 2.1
Name: flagopt
Version: 0.1.4
Summary: Command line based argument parse framework.
Home-page: https://github.com/Exahilosys/flagopt
Author: UNKNOWN
Author-email: UNKNOWN
License: MIT
Platform: UNKNOWN
Requires-Dist: multidict
